intents/__init__.py
intents/connectors/__init__.py
intents/connectors/_experimental/__init__.py
intents/connectors/_experimental/alexa/__init__.py
intents/connectors/_experimental/alexa/agent_schemas.py
intents/connectors/_experimental/alexa/connector.py
intents/connectors/_experimental/alexa/connector_test.py
intents/connectors/_experimental/alexa/dates.py
intents/connectors/_experimental/alexa/dates_test.py
intents/connectors/_experimental/alexa/export.py
intents/connectors/_experimental/alexa/fulfillment.py
intents/connectors/_experimental/alexa/fulfillment_schemas.py
intents/connectors/_experimental/alexa/fulfillment_schemas_test.py
intents/connectors/_experimental/alexa/fulfillment_test.py
intents/connectors/_experimental/alexa/language.py
intents/connectors/_experimental/alexa/language_test.py
intents/connectors/_experimental/alexa/names.py
intents/connectors/_experimental/alexa/slot_types.py
intents/connectors/_experimental/alexa/slot_types_test.py
intents/connectors/_experimental/snips/__init__.py
intents/connectors/_experimental/snips/agent_format.py
intents/connectors/_experimental/snips/connector.py
intents/connectors/_experimental/snips/connector_test.py
intents/connectors/_experimental/snips/entities.py
intents/connectors/_experimental/snips/entities_test.py
intents/connectors/_experimental/snips/export.py
intents/connectors/_experimental/snips/prediction.py
intents/connectors/_experimental/snips/prediction_format.py
intents/connectors/_experimental/snips/prediction_format_test.py
intents/connectors/_experimental/snips/prediction_test.py
intents/connectors/dialogflow_es/__init__.py
intents/connectors/dialogflow_es/agent_format.py
intents/connectors/dialogflow_es/auth.py
intents/connectors/dialogflow_es/connector.py
intents/connectors/dialogflow_es/connector_test.py
intents/connectors/dialogflow_es/entities.py
intents/connectors/dialogflow_es/entities_test.py
intents/connectors/dialogflow_es/export.py
intents/connectors/dialogflow_es/export_test.py
intents-0.3.0.dist-info/LICENSE
intents-0.3.0.dist-info/WHEEL
intents-0.3.0.dist-info/METADATA
intents-0.3.0.dist-info/RECORD
