Metadata-Version: 2.1
Name: intents
Version: 0.3.0
Summary: Define and operate Dialogflow Agents with a simple, code-first, approach
Home-page: https://github.com/dariowho/intents
License: Apache-2.0
Author: Dario
Author-email: dario.chi@inventati.org
Requires-Python: >=3.8,<4.0
Classifier: License :: OSI Approved :: Apache Software License
Classifier: Programming Language :: Python :: 3
Classifier: Programming Language :: Python :: 3.8
Provides-Extra: snips
Requires-Dist: dacite (>=1.6.0,<2.0.0)
Requires-Dist: google-cloud-dialogflow (>=2.0.0,<3.0.0)
Requires-Dist: pyyaml (>=5.4.1,<6.0.0)
Requires-Dist: snips-nlu[snips] (>=0.20.2,<0.21.0); extra == "snips"
Project-URL: Documentation, https://intents.readthedocs.io/
Project-URL: Repository, https://github.com/dariowho/intents
